ypkpathway/__init__.py
ypkpathway/_version.py
ypkpathway/gui.py
ypkpathway/qrc.py
ypkpathway/ypkpathway.py
ypkpathway/data/nb_template_pYPK0_pw.md
ypkpathway/data/nb_template_pYPK0_tp_gene_tp.md
ypkpathway/data/nb_template_pYPK0_tp_gene_tp_gap_repair.md
ypkpathway/data/nb_template_pYPKa_A_insert.md
ypkpathway/data/nb_template_pYPKa_ZE_insert.md
ypkpathway/data/pYPK0.gb
ypkpathway/data/pYPK_A.png
ypkpathway/data/pYPK_ZE.png
ypkpathway/data/pYPKa.gb
ypkpathway/data/pYPKpw.gb
ypkpathway/data/pw.png
ypkpathway/data/standard_primers.txt
ypkpathway/data/start.bat
ypkpathway/data/start.sh
ypkpathway/data/tp_g_tp.png
ypkpathway/icons/address-book-new.png
ypkpathway/icons/assemble.png
ypkpathway/icons/document-new.png
ypkpathway/icons/document-open.png
ypkpathway/icons/document-save-as.png
ypkpathway/icons/document-save.png
ypkpathway/icons/edit-find-replace.png
ypkpathway/icons/go-home.png
ypkpathway/icons/go-jump.png
ypkpathway/icons/help-browser.png
ypkpathway/icons/ipynb_icon_32x32.png
ypkpathway/icons/media-floppy.png
ypkpathway/icons/preferences-system-session.png
ypkpathway/icons/process-stop.png
ypkpathway/icons/system-log-out.png
ypkpathway/icons/view-refresh.png
ypkpathway/icons/ypkpathway.png
ypkpathway-3.0.1.dist-info/LICENSE.txt
ypkpathway-3.0.1.dist-info/METADATA
ypkpathway-3.0.1.dist-info/WHEEL
ypkpathway-3.0.1.dist-info/entry_points.txt
ypkpathway-3.0.1.dist-info/top_level.txt
ypkpathway-3.0.1.dist-info/RECORD
