Metadata-Version: 2.1
Name: ypkpathway
Version: 3.0.1
Summary: Simulation and documentation of metabolic pathway assemblies using the Yeast Pathway Kit.
Home-page: https://github.com/BjornFJohansson/ypkpathway
Author: Björn Johansson
Author-email: bjorn_johansson@bio.uminho.pt
License: LICENSE.txt
Keywords: bioinformatics
Platform: UNKNOWN
Classifier: Development Status :: 4 - Beta
Classifier: Environment :: Console
Classifier: Intended Audience :: Education
Classifier: Intended Audience :: Science/Research
Classifier: License :: OSI Approved :: BSD License
Classifier: Programming Language :: Python :: 3.6
Classifier: Programming Language :: Python :: 3.7
Classifier: Topic :: Education
Classifier: Topic :: Scientific/Engineering :: Bio-Informatics
Requires-Dist: pydna
Requires-Dist: ipython
Requires-Dist: docopt
Requires-Dist: notedown
Requires-Dist: nbformat
Requires-Dist: nbconvert
